dqtoolbundle/DQToolBundle.py
dqtoolbundle/DQToolBundleTest.py
dqtoolbundle/DQToolFactory.py
dqtoolbundle/_config/.gitignore
dqtoolbundle/_config/config.yaml
dqtoolbundle/_config/config_test.yaml
dqtoolbundle/test/DummySparkFactory.py
dq_tool_bundle-0.0.4.dist-info/entry_points.txt
dq_tool_bundle-0.0.4.dist-info/LICENSE
dq_tool_bundle-0.0.4.dist-info/WHEEL
dq_tool_bundle-0.0.4.dist-info/METADATA
dq_tool_bundle-0.0.4.dist-info/RECORD
